cosmosc2/__init__.py
cosmosc2/__version__.py
cosmosc2/api_shared.py
cosmosc2/authorization.py
cosmosc2/commands.py
cosmosc2/connection.py
cosmosc2/cosmos_api.py
cosmosc2/decorators.py
cosmosc2/environment.py
cosmosc2/exceptions.py
cosmosc2/extract.py
cosmosc2/internal_api.py
cosmosc2/limits.py
cosmosc2/stream.py
cosmosc2/stream_shared.py
cosmosc2/telemetry.py
cosmosc2/timeline_api.py
cosmosc2/tools.py
cosmosc2/json_rpc/__init__.py
cosmosc2/json_rpc/base.py
cosmosc2/json_rpc/error.py
cosmosc2/json_rpc/request.py
cosmosc2/json_rpc/response.py
cosmosc2-1.2.0.dist-info/LICENSE.txt
cosmosc2-1.2.0.dist-info/METADATA
cosmosc2-1.2.0.dist-info/WHEEL
cosmosc2-1.2.0.dist-info/top_level.txt
cosmosc2-1.2.0.dist-info/RECORD
