Metadata-Version: 2.1
Name: cosmosc2
Version: 1.2.0
Summary: Python Support for Ball Aerospace COSMOS v5
Home-page: https://github.com/BallAerospace/python-cosmosc2
Author: Ryan Melton
Author-email: rmelton@ball.com
License: GPLv3
Keywords: ball aerospace cosmos
Platform: UNKNOWN
Classifier: Development Status :: 3 - Alpha
Classifier: Intended Audience :: Developers
Classifier: Topic :: Software Development :: Libraries :: Python Modules
Classifier: License :: OSI Approved :: GNU General Public License v3 (GPLv3)
Classifier: Programming Language :: Python :: 3.7
Classifier: Programming Language :: Python :: 3.8
Classifier: Programming Language :: Python :: 3.9
Classifier: Programming Language :: Python :: 3.10
License-File: LICENSE.txt
